click_cadquery/__init__.py
click_cadquery/git.py
click_cadquery/py.typed
click_cadquery-0.2.0.dist-info/WHEEL
click_cadquery-0.2.0.dist-info/METADATA
click_cadquery-0.2.0.dist-info/RECORD
