Metadata-Version: 2.3
Name: click-cadquery
Version: 0.2.0
Summary: Click decorators for CadQuery CLI applications with automatic option generation from Pydantic models
Author: anekos
License: MIT
Classifier: Development Status :: 5 - Production/Stable
Classifier: Intended Audience :: Developers
Classifier: License :: OSI Approved :: MIT License
Classifier: Programming Language :: Python :: 3
Classifier: Programming Language :: Python :: 3.11
Classifier: Programming Language :: Python :: 3.12
Classifier: Programming Language :: Python :: 3.13
Classifier: Topic :: Software Development :: Libraries :: Python Modules
Classifier: Topic :: Scientific/Engineering
Requires-Dist: click>=8.2.1
Requires-Dist: pydantic>=2.11.7
Requires-Python: >=3.11
